terraformreviewer/__init__.py
terraformreviewer/cli.py
terraformreviewer-0.1.3.dist-info/METADATA
terraformreviewer-0.1.3.dist-info/WHEEL
terraformreviewer-0.1.3.dist-info/entry_points.txt
terraformreviewer-0.1.3.dist-info/top_level.txt
terraformreviewer-0.1.3.dist-info/RECORD
