Metadata-Version: 2.4
Name: terraformreviewer
Version: 0.1.3
Summary: Generate Terraform READMEs and inline comments using Claude
Author-email: Your Name <you@example.com>
Requires-Dist: anthropic
Requires-Dist: typer
